gmaps/__init__.py
gmaps/config.py
gmaps/constants.py
gmaps/models.py
gmaps/py.typed
gmaps/settings.py
gmaps/clients/__init__.py
gmaps/clients/_auth.py
gmaps/clients/_base.py
gmaps/clients/_clients.py
gmaps/clients/_rate_limiter.py
gmaps/clients/_retry.py
gmaps/clients/client.py
gmaps_async_client-1.0.1.dist-info/licenses/LICENSE
gmaps_async_client-1.0.1.dist-info/METADATA
gmaps_async_client-1.0.1.dist-info/WHEEL
gmaps_async_client-1.0.1.dist-info/top_level.txt
gmaps_async_client-1.0.1.dist-info/RECORD
