Metadata-Version: 2.4
Name: gmaps-async-client
Version: 1.0.1
Summary: Python wrapper for Google Maps APIs (Places & Geocoding)
Author-email: Jonathan Oren <jonathanoren98@gmail.com>
Maintainer-email: Jonathan Oren <jonathanoren98@gmail.com>
License: MIT
Project-URL: Homepage, https://github.com/asparagusbeef/gmaps-async-client
Project-URL: Documentation, https://asparagusbeef.github.io/gmaps-async-client
Project-URL: Repository, https://github.com/asparagusbeef/gmaps-async-client
Project-URL: Issues, https://github.com/asparagusbeef/gmaps-async-client/issues
Project-URL: Changelog, https://github.com/asparagusbeef/gmaps-async-client/blob/main/CHANGELOG.md
Keywords: gmaps,api,transportation,geocoding,places,autocomplete
Classifier: Development Status :: 3 - Alpha
Classifier: Intended Audience :: Developers
Classifier: License :: OSI Approved :: MIT License
Classifier: Operating System :: OS Independent
Classifier: Programming Language :: Python :: 3
Classifier: Programming Language :: Python :: 3.9
Classifier: Programming Language :: Python :: 3.10
Classifier: Programming Language :: Python :: 3.11
Classifier: Programming Language :: Python :: 3.12
Classifier: Topic :: Software Development :: Libraries :: Python Modules
Classifier: Topic :: Internet :: WWW/HTTP :: Dynamic Content
Requires-Python: >=3.9
License-File: LICENSE
Requires-Dist: httpx>=0.25.0
Requires-Dist: pydantic<3.0.0,>=2.5.0
Requires-Dist: pydantic-settings>=2.0.0
Requires-Dist: h2>=4.3.0
Provides-Extra: google
Requires-Dist: google-auth>=2.0.0; extra == "google"
Requires-Dist: google-auth-stubs>=0.3.0; extra == "google"
Provides-Extra: dev
Requires-Dist: pytest>=8.4.0; extra == "dev"
Requires-Dist: pytest-asyncio>=1.1.0; extra == "dev"
Requires-Dist: pytest-cov>=6.1.0; extra == "dev"
Requires-Dist: pytest-mock>=3.14.0; extra == "dev"
Requires-Dist: httpx[mock]>=0.25.0; extra == "dev"
Requires-Dist: respx>=0.21.0; extra == "dev"
Requires-Dist: ruff>=0.12.12; extra == "dev"
Requires-Dist: mypy>=1.17.1; extra == "dev"
Requires-Dist: black>=24.0.0; extra == "dev"
Requires-Dist: isort>=6.0.0; extra == "dev"
Requires-Dist: bandit>=1.8.6; extra == "dev"
Requires-Dist: pre-commit>=4.3.0; extra == "dev"
Requires-Dist: build>=1.3.0; extra == "dev"
Requires-Dist: twine>=6.2.0; extra == "dev"
Requires-Dist: types-psutil>=7.0.0; extra == "dev"
Provides-Extra: test
Requires-Dist: pytest>=8.4.2; extra == "test"
Requires-Dist: pytest-asyncio>=1.1.0; extra == "test"
Requires-Dist: pytest-cov>=6.2.1; extra == "test"
Requires-Dist: pytest-mock>=3.14.0; extra == "test"
Requires-Dist: httpx[mock]>=0.25.0; extra == "test"
Requires-Dist: respx>=0.21.0; extra == "test"
Requires-Dist: pytest-env>=1.1.0; extra == "test"
Requires-Dist: trio>=0.27.0; extra == "test"
Requires-Dist: python-dotenv>=1.0.0; extra == "test"
Dynamic: license-file
